[
  {
    "id": "home",
    "url": "/",
    "title": "Home",
    "modules": [
      {
        "id": 13,
        "parentId": 8,
        "module": {
          "id": "container"
        }
      },
      {
        "id": 8,
        "parentId": 0,
        "module": {
          "id": "header",
          "properties": {
            "backgroundOverlay": {
              "color": "#fff",
              "opacity": 0.2
            }
          }
        }
      },
      {
        "id": 9,
        "parentId": 13,
        "module": {
          "id": "navbar",
          "properties": {
            "gap": "40px",
            "alignItems": {
              "horizontal": "center"
            }
          }
        }
      },
      {
        "id": 10,
        "parentId": 9,
        "module": {
          "id": "nav-link",
          "properties": {
            "link": {
              "label": "Home",
              "href": "/"
            }
          }
        }
      },
      {
        "id": 11,
        "parentId": 9,
        "module": {
          "id": "nav-link",
          "properties": {
            "link": {
              "label": "About",
              "href": "/about"
            }
          }
        }
      },
      {
        "id": 12,
        "parentId": 9,
        "module": {
          "id": "nav-link",
          "properties": {
            "link": {
              "label": "Contacts",
              "href": "/contacts"
            }
          }
        }
      },
      {
        "id": 1,
        "parentId": 0,
        "module": {
          "id": "layout",
          "properties": {
            "backgroundColor": "#fff"
          }
        }
      },
      {
        "id": 2,
        "module": {
          "id": "section",
          "properties": {
            "height": "100vh",
            "backgroundImage": {
              "src": "/assets/1.jpg",
              "size": "cover",
              "attachment": "fixed"
            },
            "backgroundOverlay": {
              "color": "#000",
              "opacity": 0.45
            }
          }
        },
        "parentId": 1
      },
      {
        "id": 3,
        "module": {
          "id": "container",
          "properties": {}
        },
        "parentId": 2
      },
      {
        "id": 4,
        "module": {
          "id": "section",
          "properties": {
            "height": "100vh",
            "backgroundImage": {
              "src": "/assets/2.jpg",
              "size": "cover",
              "attachment": "fixed"
            },
            "backgroundOverlay": {
              "color": "#000",
              "opacity": 0.45
            }
          }
        },
        "parentId": 1
      },
      {
        "id": 5,
        "module": {
          "id": "container",
          "properties": {}
        },
        "parentId": 4
      },
      {
        "id": 6,
        "module": {
          "id": "section",
          "properties": {
            "height": "100vh",
            "backgroundImage": {
              "src": "/assets/3.jpg",
              "size": "cover",
              "attachment": "fixed"
            },
            "backgroundOverlay": {
              "color": "#000",
              "opacity": 0.45
            }
          }
        },
        "parentId": 1
      },
      {
        "id": 7,
        "module": {
          "id": "container",
          "properties": {}
        },
        "parentId": 6
      }
    ]
  },
  {
    "id": "about",
    "url": "/about",
    "title": "About"
  },
  {
    "id": "contacts",
    "url": "/contacts",
    "title": "Contacts"
  }
]
